{
    "homepage": "https://www.adobe.com/cn/solutions/ebook/digital-editions.html",
    "description": "Optimize your reading experience with the best eBook reader across formats.",
    "version": "4.5.11",
    "license": {
        "identifier": "Shareware"
    },
    "url": "https://adedownload.adobe.com/pub/adobe/digitaleditions/ADE_4.5_Installer.exe#/dl.7z",
    "shortcuts": [
        [
            "DigitalEditions.exe",
            "DigitalEditions"
        ]
    ],
    "checkver": {
        "url": "https://www.adobe.com/cn/solutions/ebook/digital-editions/download.html",
        "regex": ">(\\d+\\.\\d+)(?<patch>\\.\\d+) Windows",
        "replace": "$1${patch}"
    },
    "autoupdate": {
        "url": "https://adedownload.adobe.com/pub/adobe/digitaleditions/ADE_$match1_Installer.exe#/dl.7z"
    },
    "hash": "a21a9d5389728fdac6a7288953dddeea774ef2bee07f1caf7ea20bbed8f5a2c6"
}
