{
    "version": "2.5.6",
    "description": "afrog 是一款性能卓越、快速稳定、PoC 可定制化的漏洞扫描工具 - A tool for finding vulnerabilities",
    "homepage": "https://github.com/zan8in/afrog",
    "license": "MIT",
    "architecture": {
        "64bit": {
            "url": "https://github.com/zan8in/afrog/releases/download/v2.5.6/afrog_2.5.6_windows_amd64.zip",
            "hash": "25331c6d0186fe7b6389064789fcb49a359a2aade8e6e1ee4aff50c24e76ced9"
        }
    },
    "bin": "afrog.exe",
    "checkver": "github",
    "autoupdate": {
        "architecture": {
            "64bit": {
                "url": "https://github.com/zan8in/afrog/releases/download/v$version/afrog_$version_windows_amd64.zip"
            }
        }
    }
}
