{
    "version": "0.26.0",
    "description": "A cli tool for interacting with the Alertmanager API.",
    "homepage": "https://github.com/prometheus/alertmanager",
    "license": "Apache-2.0",
    "architecture": {
        "64bit": {
            "url": "https://github.com/prometheus/alertmanager/releases/download/v0.26.0/alertmanager-0.26.0.windows-amd64.tar.gz",
            "extract_dir": "alertmanager-0.26.0.windows-amd64",
            "hash": "dc26fc8f9ef8b3801069803f50ae182c8b84620de3a94e0adc90c0669bc5af76"
        },
        "32bit": {
            "url": "https://github.com/prometheus/alertmanager/releases/download/v0.26.0/alertmanager-0.26.0.windows-386.tar.gz",
            "extract_dir": "alertmanager-0.26.0.windows-386",
            "hash": "85d6619b0a16d039647865a05d2eff22c20258120900f19451e95426c229b4de"
        }
    },
    "post_install": "Remove-Item \"$dir\\alertmanager*\" -Force -Recurse",
    "bin": "amtool.exe",
    "checkver": "github",
    "autoupdate": {
        "architecture": {
            "64bit": {
                "url": "https://github.com/prometheus/alertmanager/releases/download/v$version/alertmanager-$version.windows-amd64.tar.gz",
                "extract_dir": "alertmanager-$version.windows-amd64"
            },
            "32bit": {
                "url": "https://github.com/prometheus/alertmanager/releases/download/v$version/alertmanager-$version.windows-386.tar.gz",
                "extract_dir": "alertmanager-$version.windows-386"
            }
        },
        "hash": {
            "url": "$baseurl/sha256sums.txt"
        }
    }
}
