{
    "version": "0.6.7",
    "description": "App Flowy. An open-source alternative to Notion. You are in charge of your data and customizations",
    "homepage": "https://www.appflowy.io",
    "license": "AGPL-3.0-only",
    "changelog": "https://github.com/AppFlowy-IO/AppFlowy/releases",
    "url": "https://github.com/AppFlowy-IO/AppFlowy/releases/download/0.6.7/AppFlowy-0.6.7-windows-x86_64.zip",
    "hash": "5c70278c7874552c6d8e14a8f85ea4a8405726c074ae1ddfd9ca66d67c702c94",
    "extract_dir": "AppFlowy",
    "shortcuts": [
        [
            "app_flowy.exe",
            "AppFlowy"
        ]
    ],
    "checkver": {
        "url": "https://github.com/AppFlowy-IO/appflowy/releases/latest",
        "regex": "/tag/(?<version>[\\d.]+(_(beta|alpha).\\d+)?)"
    },
    "autoupdate": {
        "url": "https://github.com/AppFlowy-IO/AppFlowy/releases/download/$version/AppFlowy-$version-windows-x86_64.zip"
    }
}
