{
    "version": "6.15.1",
    "homepage": "https://birdfont.org",
    "description": "Birdfont is a free font editor which lets you create vector graphics and export TTF, OTF, EOT and SVG fonts. The editor has good support for both monochrome and color font formats.",
    "license": "GNU GPL",
    "url": "https://birdfont.org/download/birdfont-6.15.1-free.exe#/dl.7z",
    "hash": "4d3b9d288f7f24220437d35d5966d38500757cc470bfd598257dab0c31c34da5",
    "pre_install": "Remove-Item \"$dir\\uninstall*\" -Force",
    "shortcuts": [
        [
            "birdfont.exe",
            "Birdfont"
        ]
    ],
    "checkver": {
        "url": "https://birdfont.org/purchase.php",
        "regex": "download/birdfont-([\\d.]+)"
    },
    "autoupdate": {
        "url": "https://birdfont.org/download/birdfont-$version-free.exe#/dl.7z"
    }
}
