{
    "version": "1.9.0.247",
    "description": "Create sprite sheets and dynamic text effects for HTML, games, toolstrips, and more.",
    "homepage": "https://www.cyotek.com/cyotek-spriter",
    "license": "Proprietary",
    "url": "https://www.cyotek.com/downloads/get/setup-cyospr-1.9.0-build-247.exe#/setup-cyospr.exe",
    "hash": "3de3da4a5d37cbd87f66bfa627e50e2a345dfab67cfc3b468bee154212cdf713",
    "innosetup": true,
    "bin": "spriter.exe",
    "shortcuts": [
        [
            "spriter.exe",
            "Cyotek Spriter"
        ]
    ],
    "checkver": {
        "url": "https://www.cyotek.com/cyotek-spriter/revision-history",
        "regex": "Version ([\\d.]+) (?!Beta)"
    },
    "autoupdate": {
        "url": "https://www.cyotek.com/downloads/get/setup-cyospr-$matchHead-build-$buildVersion.exe#/setup-cyospr.exe",
        "hash": "$url.sha256"
    }
}
