{
    "homepage": "http://softwareok.com/?seite=Microsoft/DesktopNoteOK",
    "description": "Desktop notes",
    "license": "freeware",
    "version": "3.71",
    "architecture": {
        "64bit": {
            "url": "http://softwareok.com/Download/DesktopNoteOK_x64_Portable.zip",
            "hash": "c1968d814ed39cdedd6ee5eaecb80ed6d5f48a56f4123dd0460b0b59c257d0db"
        },
        "32bit": {
            "url": "http://softwareok.com/Download/DesktopNoteOK_Portable.zip",
            "hash": "6ac8edb10daca459b3e4bfbb6899c8345a7504c8ae9168e544f98fdd3df69d69"
        }
    },
    "pre_install": [
        "$exefile = (Get-ChildItem \"$dir\" '*.exe' | Select-Object -First 1).FullName",
        "Rename-Item \"$exefile\" \"$dir\\DesktopNoteOK.exe\"",
        "if(!(Test-Path \"$persist_dir\\DesktopNoteOK.ini\")) {",
        "    New-Item \"$dir\\DesktopNoteOK.ini\" -Type File -Force | Out-Null",
        "}"
    ],
    "bin": "DesktopNoteOK.exe",
    "shortcuts": [
        [
            "DesktopNoteOK.exe",
            "DesktopNoteOK"
        ]
    ],
    "persist": "DesktopNoteOK.ini",
    "checkver": "DesktopNoteOK ([\\d.]+)",
    "autoupdate": {
        "architecture": {
            "64bit": {
                "url": "http://softwareok.com/Download/DesktopNoteOK_x64_Portable.zip",
                "hash": {
                    "url": "http://softwareok.com/?Download=DesktopNoteOK",
                    "find": "DesktopNoteOK_x64_Portable\\.zip.+?target=_blank>($sha256)"
                }
            },
            "32bit": {
                "url": "http://softwareok.com/Download/DesktopNoteOK_Portable.zip",
                "hash": {
                    "url": "http://softwareok.com/?Download=DesktopNoteOK",
                    "find": "DesktopNoteOK_Portable\\.zip.+?target=_blank>($sha256)"
                }
            }
        }
    }
}
