{
    "version": "2023-09-13-run472-id6177242445",
    "description": "Revival of the well known .NET debugger and assembly editor, dnSpy",
    "homepage": "https://github.com/dnSpyEx/dnSpy",
    "license": "GPL-3.0-only",
    "architecture": {
        "64bit": {
            "url": "https://nightly.link/dnSpyEx/dnSpy/workflows/build/master/dnSpy-net-win64.zip#/dl.7z",
            "hash": "efd619274a9172958f95c0e40c4b8ee73df34d12fb4681a7de5d9290a05d9489"
        },
        "32bit": {
            "url": "https://nightly.link/dnSpyEx/dnSpy/workflows/build/master/dnSpy-net-win32.zip#/dl.7z",
            "hash": "6085d6039453d2ade5f49a1e17b08c2bb93b56b399fcd7c692d828eea95fe547"
        }
    },
    "bin": [
        [
            "dnSpy.Console.exe",
            "dnSpyEx.Console-nightly"
        ],
        [
            "dnSpy.exe",
            "dnSpyEx-nightly"
        ]
    ],
    "shortcuts": [
        [
            "dnSpy.exe",
            "dnSpyEx Nightly"
        ]
    ],
    "checkver": {
        "url": "https://github.com/dnSpyEx/dnSpy/actions/workflows/build.yml?query=branch%3Amaster+is%3Asuccess",
        "regex": "<a class=\"Link--primary css-truncate css-truncate-target\" .*? aria-label=\"Run (?<runCount>[\\d]+) of.*? href=\".*?/runs/(?<runId>[\\d]+?)\">[\\S\\s]+? datetime=\"(?<buildDate>\\d{4}-\\d{2}-\\d{2})T",
        "replace": "${buildDate}-run${runCount}-id${runId}"
    },
    "autoupdate": {
        "architecture": {
            "64bit": {
                "url": "https://nightly.link/dnSpyEx/dnSpy/workflows/build/master/dnSpy-net-win64.zip#/dl.7z"
            },
            "32bit": {
                "url": "https://nightly.link/dnSpyEx/dnSpy/workflows/build/master/dnSpy-net-win32.zip#/dl.7z"
            }
        }
    }
}
