{
    "version": "1.0",
    "description": "A small command line utility which allows you to generate Delphi package files (DPK) based on the given template file.",
    "homepage": "https://www.pazera-software.com/products/dpk-generator/",
    "license": "Freeware",
    "architecture": {
        "64bit": {
            "url": "https://www.pazera-software.com/files/DpkGen_PORTABLE_64bit.zip",
            "hash": "e9e9b3bde978b7ac0dff899c52ad7d71c69f550d85b575ce24e3b68bfb957bf7"
        },
        "32bit": {
            "url": "https://www.pazera-software.com/files/DpkGen_PORTABLE_32bit.zip",
            "hash": "8a97ebb3497e010645142a946c67aee5aca5e315b9d37bee36972ba3623ad78e"
        }
    },
    "bin": "DpkGen.exe",
    "checkver": {
        "regex": "Version:</div>([\\d.]+)"
    },
    "autoupdate": {
        "architecture": {
            "64bit": {
                "url": "https://www.pazera-software.com/files/DpkGen_PORTABLE_64bit.zip"
            },
            "32bit": {
                "url": "https://www.pazera-software.com/files/DpkGen_PORTABLE_32bit.zip"
            }
        }
    }
}
