{
    "homepage": "https://www.emeditor.com/",
    "version": "21.3.0",
    "description": "EmEditor is a fast, lightweight, yet extensible, easy-to-use text editor for Windows.",
    "license": "https://www.emeditor.com/#toggle-id-4",
    "architecture": {
        "64bit": {
            "url": "https://emeditor.blob.core.windows.net/emed64_21.3.0_portable.zip",
            "hash": "c2f31776a09e3159b1fb194d22a70e3867c875776a0f47983de9e6b1347b139b"
        },
        "32bit": {
            "url": "https://emeditor.blob.core.windows.net/emed32_21.3.0_portable.zip",
            "hash": "22c76a9cc97265cfd3ca6f79706272050ec527fa1c845e4b4c2690c23edb7691"
        }
    },
    "bin": "EmEditor.exe",
    "shortcuts": [
        [
            "EmEditor.exe",
            "EmEditor"
        ]
    ],
    "post_install": "Remove-Item \"$dir\\eeUseIni.ini\"",
    "checkver": {
        "url": "https://www.emeditor.com/download/",
        "re": "<h3>Download latest version: v([\\d.]+)</h3>"
    },
    "autoupdate": {
        "architecture": {
            "64bit": {
                "url": "https://emeditor.blob.core.windows.net/emed64_$version_portable.zip"
            },
            "32bit": {
                "url": "https://emeditor.blob.core.windows.net/emed32_$version_portable.zip"
            }
        }
    }
}
