{
    "version": "15.17.1",
    "description": "Epic Games Launcher. Allow players to purchase, install and keep their games up to date",
    "homepage": "https://www.epicgames.com/",
    "license": {
        "identifier": "Freeware",
        "url": "https://www.epicgames.com/site/en-US/tos"
    },
    "url": "https://launcher-public-service-prod06.ol.epicgames.com/launcher/api/installer/download/EpicGamesLauncherInstaller.msi",
    "hash": "6f3f486d7a8409fc174198818c039152c6268bd9fdf210ee6be1c91bf832b7e9",
    "extract_dir": "Epic Games\\Launcher",
    "shortcuts": [
        [
            "Portal\\Binaries\\Win32\\EpicGamesLauncher.exe",
            "Epic Games Launcher"
        ]
    ],
    "checkver": {
        "url": "https://repology.org/project/epic-games/versions",
        "regex": "cask/epic-games\">([\\d.]+)"
    },
    "autoupdate": {
        "url": "https://launcher-public-service-prod06.ol.epicgames.com/launcher/api/installer/download/EpicGamesLauncherInstaller.msi"
    }
}
