{
    "homepage": "https://www.ponsoftware.com/",
    "version": "9.73",
    "license": "https://www.ponsoftware.com/archiver/regist.htm",
    "architecture": {
        "64bit": {
            "url": "https://www.ponsoftware.com/archiver/explzh/explz973_x64.exe#/dl.7z",
            "hash": "cf6d1e6c515acf68b18e91905f62108c4e4cca2454f56911a7d6167f0d4e585c"
        },
        "32bit": {
            "url": "https://www.ponsoftware.com/archiver/explzh/explz973.exe#/dl.7z",
            "hash": "dd5580133ce294b633ffa5cd5bd221009231b7e29b4bb2689c45d0aa5edfa5d7"
        }
    },
    "installer": {
        "script": [
            "",
            "InfDefaultInstall \"$dir\\x64\\EXPLZH.INF\"",
            ""
        ]
    },
    "bin": "Explzh.exe",
    "shortcuts": [
        [
            "Explzh.exe",
            "Explzh"
        ]
    ],
    "post_install": [
        "",
        "# Parrent path",
        "$regpath = 'HKCU:\\Software\\Pon\\'",
        "if (-not (Test-Path \"$regpath\")) { New-Item -Path \"$regpath\" | Out-Null }",
        "$regpath = 'HKCU:\\Software\\Pon\\Explzh\\'",
        "if (-not (Test-Path \"$regpath\")) { New-Item -Path \"$regpath\" | Out-Null }",
        "# ExplzhDir",
        "$regpath = 'HKCU:\\Software\\Pon\\Explzh\\Folders\\'",
        "if (-not (Test-Path \"$regpath\")) { New-Item -Path \"$regpath\" | Out-Null }",
        "$regname = 'ExplzhDir'",
        "$regvalue = Get-ItemProperty -Path \"$regpath\" -Name \"$regname\" -ErrorAction SilentlyContinue",
        "if ($regvalue -eq $null) {",
        "Set-ItemProperty \"$regpath\" -Name \"$regname\" -Value \"$dir\"",
        "}",
        ""
    ],
    "uninstaller": {
        "script": [
            "",
            "Copy-Item \"$dir\\associate.exe\" $Env:Temp",
            "Copy-Item \"$dir\\install.exe\" $Env:Temp",
            "&\"$Env:Temp\\install.exe\" \"/d\"",
            ""
        ]
    },
    "checkver": {
        "url": "https://www.ponsoftware.com/archiver/download.htm",
        "re": "Explzh Ver\\.([\\d.]+) \\("
    },
    "autoupdate": {
        "architecture": {
            "64bit": {
                "url": "https://www.ponsoftware.com/archiver/explzh/explz$cleanVersion_x64.exe#/dl.7z"
            },
            "32bit": {
                "url": "https://www.ponsoftware.com/archiver/explzh/explz$cleanVersion.exe#/dl.7z"
            }
        }
    }
}
