{
    "version": "N-102759-g0e4ae779cd-g604924a069+5",
    "description": "A complete, cross-platform solution to record, convert and stream audio and video.",
    "homepage": "https://ffmpeg.org",
    "license": "GPL-3.0-or-later",
    "url": "https://jeremylee.sh/data/bin/ffmpeg.7z",
    "hash": "2e40dec7bbca6f3357e22060398241ed451c6e30fe7989f9e509c32820f3b27b",
    "bin": "ffmpeg.exe",
    "checkver": {
        "url": "https://jeremylee.sh/bin.html",
        "regex": "</span><span class=\"db\">(.*?)<\\/span>"
    },
    "autoupdate": {
        "url": "https://jeremylee.sh/data/bin/ffmpeg.7z",
        "hash": "$url.sha256"
    }
}
