{
    "version": "150.0a1.20260307095200",
    "description": "Nightly builds of Firefox: the popular open source web browser.",
    "homepage": "https://www.mozilla.org/fa-IR/firefox/nightly/",
    "license": "MPL-2.0",
    "architecture": {
        "64bit": {
            "url": "https://archive.mozilla.org/pub/firefox/nightly/latest-mozilla-central-l10n/firefox-150.0a1.fa.win64.zip",
            "hash": "sha512:86a297294a66c364cf327a5f2c312cd5db6e93437741b536769723231087e373ba7f728ca99fb1fec7ec5eebd03725f3fbae65f020d646eabfa3873032cfbc23"
        },
        "32bit": {
            "url": "https://archive.mozilla.org/pub/firefox/nightly/latest-mozilla-central-l10n/firefox-150.0a1.fa.win32.zip",
            "hash": "sha512:89d22fc0c395c1eee1d72a4ffd9120a4ddf344c95905d69a5941ee27fa1a60a3925b72ecb9ad77e676443346875d3e069df1981bbbca32c45c9f8930b663c825"
        }
    },
    "extract_dir": "firefox",
    "bin": [
        [
            "firefox.exe",
            "firefox-nightly-fa",
            "-profile \"$dir\\profile\""
        ]
    ],
    "shortcuts": [
        [
            "firefox.exe",
            "Firefox Nightly (fa)",
            "-profile \"$dir\\profile\""
        ]
    ],
    "persist": "profile",
    "checkver": {
        "url": "https://aus5.mozilla.org/update/6/Firefox/60.0/_/WINNT_x86_64-msvc-x64/en-US/nightly/_/_/_/_/update.xml",
        "regex": "appVersion=\"([\\w.]+)\".*?buildID=\"((?<yyyy>\\d{4})(?<mm>\\d{2})(?<dd>\\d{2})(?<hr>\\d{2})(?<mi>\\d{2})(?<se>\\d{2}))",
        "replace": "${1}.${2}"
    },
    "autoupdate": {
        "architecture": {
            "64bit": {
                "url": "https://archive.mozilla.org/pub/firefox/nightly/latest-mozilla-central-l10n/firefox-$majorVersion.$minorVersion.fa.win64.zip",
                "hash": {
                    "url": "$baseurl/firefox-$majorVersion.$minorVersion.fa.win64.checksums"
                }
            },
            "32bit": {
                "url": "https://archive.mozilla.org/pub/firefox/nightly/latest-mozilla-central-l10n/firefox-$majorVersion.$minorVersion.fa.win32.zip",
                "hash": {
                    "url": "$baseurl/firefox-$majorVersion.$minorVersion.fa.win32.checksums"
                }
            }
        }
    }
}
