{
    "version": "121.0a1.20231105213814",
    "description": "Nightly builds of Firefox: the popular open source web browser.",
    "homepage": "https://www.mozilla.org/fa-IR/firefox/nightly/",
    "license": "MPL-2.0",
    "architecture": {
        "64bit": {
            "url": "https://archive.mozilla.org/pub/firefox/nightly/latest-mozilla-central-l10n/firefox-121.0a1.fa.win64.zip",
            "hash": "sha512:3b890398ccd331e3d5b7a5efd256c3e472fe8738ef9516371451d61bb92effe8c74121d91304edd5db6b879493ceef03f886d629067bf6753e9c39f19e1f3123"
        },
        "32bit": {
            "url": "https://archive.mozilla.org/pub/firefox/nightly/latest-mozilla-central-l10n/firefox-121.0a1.fa.win32.zip",
            "hash": "sha512:793d329bfbfcbb2cf3a93cf587e47339aac3a0f193b1a6c82b863180fc7700295e1950a5536bc1286d58615e3d0a488290c758eac14771e755b557001b958713"
        }
    },
    "extract_dir": "firefox",
    "bin": [
        [
            "firefox.exe",
            "firefox-nightly-fa",
            "-profile \"$dir\\profile\""
        ]
    ],
    "shortcuts": [
        [
            "firefox.exe",
            "Firefox Nightly (fa)",
            "-profile \"$dir\\profile\""
        ]
    ],
    "persist": "profile",
    "checkver": {
        "url": "https://aus5.mozilla.org/update/6/Firefox/60.0/_/WINNT_x86_64-msvc-x64/en-US/nightly/_/_/_/_/update.xml",
        "regex": "appVersion=\"([\\w.]+)\".*?buildID=\"((?<yyyy>\\d{4})(?<mm>\\d{2})(?<dd>\\d{2})(?<hr>\\d{2})(?<mi>\\d{2})(?<se>\\d{2}))",
        "replace": "${1}.${2}"
    },
    "autoupdate": {
        "architecture": {
            "64bit": {
                "url": "https://archive.mozilla.org/pub/firefox/nightly/latest-mozilla-central-l10n/firefox-$majorVersion.$minorVersion.fa.win64.zip",
                "hash": {
                    "url": "$baseurl/firefox-$majorVersion.$minorVersion.fa.win64.checksums"
                }
            },
            "32bit": {
                "url": "https://archive.mozilla.org/pub/firefox/nightly/latest-mozilla-central-l10n/firefox-$majorVersion.$minorVersion.fa.win32.zip",
                "hash": {
                    "url": "$baseurl/firefox-$majorVersion.$minorVersion.fa.win32.checksums"
                }
            }
        }
    }
}
