{
    "version": "20231224075759-1b0ccd8b9",
    "description": "Snapshot releases of the video transcoder with extensive support for multiple formats. (CLI version)",
    "homepage": "https://handbrake.fr",
    "license": "GPL-2.0-only",
    "architecture": {
        "64bit": {
            "url": "https://github.com/HandBrake/HandBrake-snapshots/releases/download/win/HandBrakeCLI-20231224075759-1b0ccd8b9-master-win-x86_64.zip",
            "hash": "10a831f06c12001408d5dd47206247d5d128e9c5e09447d1793758780e076448"
        }
    },
    "bin": "HandBrakeCLI.exe",
    "checkver": {
        "url": "https://github.com/HandBrake/handbrake-snapshots/releases/tag/win",
        "regex": "<td>HandBrakeCLI-([\\d]+-[\\w]+)-master-win-x86_64.zip</td>"
    },
    "autoupdate": {
        "architecture": {
            "64bit": {
                "url": "https://github.com/HandBrake/HandBrake-snapshots/releases/download/win/HandBrakeCLI-$version-master-win-x86_64.zip",
                "hash": {
                    "url": "https://github.com/HandBrake/handbrake-snapshots/releases/tag/win",
                    "regex": "<td>$sha256</td>\\s+<td>HandBrakeCLI-([\\d]+-[\\w]+)-master-win-x86_64.zip</td>"
                }
            }
        }
    }
}
