{
    "version": "20240522054916-ac399aa93",
    "description": "Snapshot releases of the video transcoder with extensive support for multiple formats. (CLI version)",
    "homepage": "https://handbrake.fr",
    "license": "GPL-2.0-only",
    "architecture": {
        "64bit": {
            "url": "https://github.com/HandBrake/HandBrake-snapshots/releases/download/win/HandBrakeCLI-20240522054916-ac399aa93-master-win-x86_64.zip",
            "hash": "0da8fd5a24308744e18fb3218e23756b5e07ce920e66f6e34109a51d5464b98f"
        }
    },
    "bin": "HandBrakeCLI.exe",
    "checkver": {
        "url": "https://github.com/HandBrake/handbrake-snapshots/releases/tag/win",
        "regex": "<td>HandBrakeCLI-([\\d]+-[\\w]+)-master-win-x86_64.zip</td>"
    },
    "autoupdate": {
        "architecture": {
            "64bit": {
                "url": "https://github.com/HandBrake/HandBrake-snapshots/releases/download/win/HandBrakeCLI-$version-master-win-x86_64.zip",
                "hash": {
                    "url": "https://github.com/HandBrake/handbrake-snapshots/releases/tag/win",
                    "regex": "<td>$sha256</td>\\s+<td>HandBrakeCLI-([\\d]+-[\\w]+)-master-win-x86_64.zip</td>"
                }
            }
        }
    }
}
