{
    "version": "2.2.11",
    "description": "Windows-GUI for Inno Setup Unpacker.",
    "homepage": "https://www.rathlev-home.de/index-e.html?tools/prog-e.html#unpack",
    "license": "Freeware",
    "url": "https://www.rathlev-home.de/tools/download/innounpacker.zip",
    "hash": "506a1dedaf59ff757cbc09a405a2ce71a5465a465b7abf55bba6c351d5708bc6",
    "shortcuts": [
        [
            "InnoUnpack.exe",
            "InnoUnpacker"
        ]
    ],
    "checkver": {
        "url": "https://www.rathlev-home.de/tools/prog-e.html",
        "regex": "Windows InnoUnpacker\\s([\\d.]+)"
    },
    "autoupdate": {
        "url": "https://www.rathlev-home.de/tools/download/innounpacker.zip"
    }
}
