{
    "version": "1.1",
    "description": "JeecgBoot密码离线爆破工具",
    "homepage": "https://github.com/ssrsec/JeecgBoot-offline-brute",
    "license": "UNKNOWN",
    "suggest": {
        "java": "sec/oraclejre8"
    },
    "url": "https://github.com/ssrsec/JeecgBoot-offline-brute/releases/download/1.1/JeecgBoot-offline-brute-1.0-SNAPSHOT.jar#/JeecgBoot-offline-brute.jar",
    "hash": "sha256:1336DF8B84F431DBA075BFCD0594CEA42F696B1F38CEAC4B1EA8811ECC344B93",
    "post_install": [
        "Invoke-WebRequest -URI \"https://github.com/ssrsec/JeecgBoot-offline-brute/raw/refs/heads/master/data.json\" -OutFile \"$dir\\data.json\"",
        "Invoke-WebRequest -URI \"https://github.com/ssrsec/JeecgBoot-offline-brute/raw/refs/heads/master/pass.txt\" -OutFile \"$dir\\pass.txt\""
    ],
    "pre_install": [
        "Set-Content \"$dir\\JeecgBoot-offline-brute.bat\" '@pushd %~dp0",
        "@call oraclejre8",
        "@cmd /c java.exe -jar \"JeecgBoot-offline-brute.jar\" %*",
        "@popd' -Encoding Ascii"
    ],
    "bin": "JeecgBoot-offline-brute.bat",
    "checkver": "github",
    "autoupdate": {
        "url": "https://github.com/ssrsec/JeecgBoot-offline-brute/releases/download/v$version/JeecgBoot-offline-brute-1.0-SNAPSHOT.jar#/JeecgBoot-offline-brute.jar"
    },
    "notes": [
        "【工具类型】: Java工具",
        "【主要功能】: JeecgBoot密码离线爆破工具",
        "【适用场景】: 根据描述推断的适用场景",
        "【技术特点】: 基于Java开发，需Java运行环境"
    ]
}
