{
    "version": "1.13.3",
    "description": "The kubectl plugin for cert-manager.",
    "homepage": "https://cert-manager.io/",
    "license": "Apache-2.0",
    "architecture": {
        "64bit": {
            "url": "https://github.com/cert-manager/cert-manager/releases/download/v1.13.3/kubectl-cert_manager-windows-amd64.tar.gz",
            "hash": "4c1985e55bb934245a259d5f662f4a0897b72b5d4f921d0d95000bca916bc488"
        }
    },
    "bin": "kubectl-cert_manager.exe",
    "checkver": {
        "github": "https://github.com/cert-manager/cert-manager"
    },
    "autoupdate": {
        "architecture": {
            "64bit": {
                "url": "https://github.com/cert-manager/cert-manager/releases/download/v$version/kubectl-cert_manager-windows-amd64.tar.gz"
            }
        }
    }
}
