{
    "version": "6.2.0-beta.2",
    "description": "An Arknights assistant, supports ZH and EN client",
    "homepage": "https://www.maa.plus/",
    "license": "AGPL-3.0",
    "url": "https://github.com/MaaAssistantArknights/MaaAssistantArknights/releases/download/v6.2.0-beta.2/MAA-v6.2.0-beta.2-win-x64.zip",
    "hash": "7d1d078f4834bd3ba855cddb77b871ccf36ff0420ff85cab23c24900dc83e6da",
    "bin": "MAA.exe",
    "shortcuts": [
        [
            "MAA.exe",
            "MAA Assistant Arknights"
        ]
    ],
    "persist": [
        "config",
        "debug"
    ],
    "checkver": {
        "url": "https://api.github.com/repos/MaaAssistantArknights/MaaAssistantArknights/releases",
        "regex": "/releases/tag/v([\\d.]+(-alpha|-beta|-rc)?(\\.\\d+)?)"
    },
    "autoupdate": {
        "url": "https://github.com/MaaAssistantArknights/MaaAssistantArknights/releases/download/v$version/MAA-v$version-win-x64.zip"
    }
}
