{
    "version": "142.0.3595.19",
    "description": "The chromium based Microsoft Edge browser (Beta Channel)",
    "homepage": "https://www.microsoft.com/en-us/edge",
    "license": "Freeware",
    "architecture": {
        "64bit": {
            "url": "https://dorado-api.deno.dev/edge?arch=64&channel=beta&version=142.0.3595.19&dl#/MicrosoftEdge-142.0.3595.19-x64.7z",
            "hash": "97e3a5dd8238a0a6e2599f9d915756dcbad8794f19dfc954f90380c4fd493dad"
        },
        "arm64": {
            "url": "https://dorado-api.deno.dev/edge?arch=arm64&channel=beta&version=142.0.3595.19&dl#/MicrosoftEdge-142.0.3595.19-arm64.7z",
            "hash": "a81ae6e914f7e0417b6fabb001c4e563406a34336b11cdfb7c033047d572eb82"
        }
    },
    "installer": {
        "script": "Expand-7zipArchive -Path \"$dir\\MSEDGE.7z\" -ExtractDir \"Chrome-bin\\$version\" -Removal"
    },
    "shortcuts": [
        [
            "msedge.exe",
            "Microsoft Edge Beta",
            "--force-device-scale-factor=1.5"
        ]
    ],
    "post_install": [
        "$runtimeCache = \"$env:LocalAppData\\Microsoft\\Edge Beta\\User Data\"",
        "$runtimeCachePersist = \"$persist_dir\\User Data\"",
        "if (Test-Path $runtimeCachePersist) {",
        "    Remove-Item -Path $runtimeCache -Force -Recurse -ErrorAction SilentlyContinue",
        "} elseif (Test-Path $runtimeCache) {",
        "    Move-Item -Path $runtimeCache -Destination $runtimeCachePersist -Force",
        "}",
        "New-DirectoryJunction $runtimeCache $runtimeCachePersist | Out-Null"
    ],
    "post_uninstall": [
        "$runtimeCache = \"$env:LocalAppData\\Microsoft\\Edge Beta\\User Data\"",
        "Remove-Item -Path $runtimeCache -Force -Recurse -ErrorAction SilentlyContinue"
    ],
    "persist": "User Data",
    "checkver": {
        "url": "https://dorado-api.deno.dev/edge?arch=64&channel=beta",
        "jsonpath": "$.Version"
    },
    "autoupdate": {
        "architecture": {
            "64bit": {
                "url": "https://dorado-api.deno.dev/edge?arch=64&channel=beta&version=$version&dl#/MicrosoftEdge-$version-x64.7z",
                "hash": {
                    "url": "https://dorado-api.deno.dev/edge?arch=64&channel=beta&version=$version",
                    "jsonpath": "$.Hashes.Sha256"
                }
            },
            "arm64": {
                "url": "https://dorado-api.deno.dev/edge?arch=arm64&channel=beta&version=$version&dl#/MicrosoftEdge-$version-arm64.7z",
                "hash": {
                    "url": "https://dorado-api.deno.dev/edge?arch=arm64&channel=beta&version=$version",
                    "jsonpath": "$.Hashes.Sha256"
                }
            }
        }
    }
}
