{
    "version": "2021.1.3-211.7628.1405",
    "description": "MPS. The Domain-Specific language creator by JetBrains.",
    "homepage": "https://www.jetbrains.com/mps/",
    "license": {
        "identifier": "Proprietary",
        "url": "https://www.jetbrains.com/store/license.html"
    },
    "changelog": "https://www.jetbrains.com/mps/whatsnew/",
    "url": "https://download.jetbrains.com/mps/2021.1/MPS-2021.1.3.exe#/cosi.7z",
    "hash": "32e8ed8e859f3ad832d2efa0ead5576c088e565e6d17c393d90590f9167228c0",
    "extract_to": "IDE",
    "pre_install": "Remove-Item \"$dir\\IDE\\`$*\" -Force -Recurse",
    "bin": "IDE\\bin\\mps.bat",
    "shortcuts": [
        [
            "IDE\\bin\\mps.bat",
            "JetBrains\\MPS",
            "",
            "IDE\\bin\\mps.ico"
        ]
    ],
    "persist": "IDE\\bin\\idea.properties",
    "checkver": {
        "url": "https://data.services.jetbrains.com/products/releases?code=MPS&latest=true&platform=zip&type=release",
        "regex": "version\":\"(?<ver>[\\d.]+)\".*\"build\":\"(?<build>[\\d.]+)\"",
        "replace": "${ver}-${build}"
    },
    "autoupdate": {
        "url": "https://download.jetbrains.com/mps/$majorVersion.$minorVersion/MPS-$matchHead.exe#/cosi.7z",
        "hash": {
            "url": "$url.sha256"
        }
    }
}
