{
    "version": "119.0.2151.93",
    "description": "Fast, secure, and free web browser, built for the modern web based",
    "homepage": "https://www.microsoft.com/en-us/edge",
    "license": {
        "identifier": "Proprietary Software"
    },
    "architecture": {
        "64bit": {
            "url": "http://msedge.f.tlu.dl.delivery.mp.microsoft.com/filestreamingservice/files/0e0873f1-66c7-48f8-871f-343e19810860?P1=1701747055&P2=404&P3=2&P4=hkcrYeMuafGsP6uzNaKfxMltWO%2bCN7mXkI2%2bx%2fJwGT4jg33BakzeZIUufVCbNG1mBydf7DdwmUdMFHjXLHgIsA%3d%3d%3d%3d3d3d#/dl.7z",
            "hash": "aff06f4b175c127956b1e41dfbcc026cec8ea9c660300f2c2ef548f73122308c"
        }
    },
    "pre_install": [
        "Expand-7zipArchive \"$dir\\MSEDGE.7z\" -ExtractDir 'Chrome-bin' -Removal",
        "Rename-Item \"$dir\\$version\" \"$dir\\current\" "
    ],
    "bin": [
        [
            "current\\msedge.exe",
            "msedge-stable",
            "--user-data-dir=\"$dir\\User Data\""
        ]
    ],
    "shortcuts": [
        [
            "current\\msedge.exe",
            "Edge Stable",
            "--user-data-dir=\"$dir\\User Data\""
        ]
    ],
    "persist": "User Data",
    "checkver": {
        "url": "https://42wim.github.io/edgeupdates/stable.txt",
        "regex": "(?sm)(?<version>(.*?)):http://(?<64>(.*))"
    },
    "autoupdate": {
        "architecture": {
            "64bit": {
                "url": "http://$match64#/dl.7z",
                "hash": {
                    "url": "https://42wim.github.io/edgeupdates/stable.sha256"
                }
            }
        }
    }
}
