{
    "version": "1.88.05.94-240512GK",
    "description": "WinPE Commander，功能强大的 WinPE 命令解释工具！",
    "homepage": "https://pecmd.net/thread-15.htm",
    "license": "",
    "architecture": {
        "64bit": {
            "bin": [
                "x64\\PECMD.exe",
                "x64\\PECMDEDIT.exe"
            ],
            "shortcuts": [
                [
                    "x64\\PECMD.exe",
                    "PECMD"
                ],
                [
                    "x64\\PECMDEDIT.exe",
                    "PECMDEDIT"
                ]
            ]
        },
        "32bit": {
            "bin": [
                "PECMD.exe",
                "PECMDEDIT.exe"
            ],
            "shortcuts": [
                [
                    "PECMD.exe",
                    "PECMD"
                ],
                [
                    "PECMDEDIT.exe",
                    "PECMDEDIT"
                ]
            ]
        }
    },
    "url": "https://api.xrgzs.top/lanzou/?url=https://www.lanzoui.com/iS52f26ttyab&type=down#/dl.7z",
    "hash": "c281ad4520e9b12d9ff2b41d270913107fdce831e7ad32146a053155f3bd5144",
    "checkver": {
        "script": [
            ". \"$pwd\\bin\\utils.ps1\"",
            "$f = Get-LanzouList \"https://www.lanzoui.com/b279972\" | Where-Object { $_.name_all -like \"PECMD2012*测试.7z\" } | Select-Object -First 1",
            "$n = $f.name_all -replace 'Stable', ''",
            "$n + '=====' + $f.id"
        ],
        "regex": "PECMD2012.(.*)测试.7z=====(?<sharekey>.*)"
    },
    "autoupdate": {
        "url": "https://api.xrgzs.top/lanzou/?url=https://www.lanzoui.com/$matchSharekey&type=down#/dl.7z"
    }
}
