{
    "homepage": "https://pixpinapp.com/",
    "description": "功能强大使用简单的截图/贴图工具，帮助你提高效",
    "version": "3.4.2.1",
    "license": "Freeware",
    "architecture": {
        "64bit": {
            "url": "https://download.pixpinapp.com/PixPin_win_3.4.2.1.zip",
            "hash": "e1bd82d1851a69790a4d60673c4193a58901aa896d6adba901fd150d85676e9a"
        }
    },
    "extract_dir": "PixPin",
    "shortcuts": [
        [
            "PixPin.exe",
            "PixPin"
        ]
    ],
    "persist": [
        "Config",
        "Data",
        "History"
    ],
    "checkver": {
        "url": "https://api.viewdepth.cn/app_info?app_id=pixpin&update_type=1&sys=win&ver=0.0.0",
        "jsonpath": "$.ver_info.version"
    },
    "autoupdate": {
        "architecture": {
            "64bit": {
                "url": "https://download.pixpinapp.com/PixPin_win_$version.zip"
            }
        }
    }
}
