{
    "version": "1.0.10",
    "description": "Playit.gg is a networking service that enables users to host game servers at home, making them accessible to players worldwide through its custom tunneling software and Anycast Network",
    "homepage": "https://playit.gg/",
    "license": {
        "identifier": "BSD-2-Clause",
        "url": "https://github.com/playit-cloud/playit-agent/blob/master/LICENSE.txt"
    },
    "architecture": {
        "32bit": {
            "url": "https://github.com/playit-cloud/playit-agent/releases/download/v1.0.10/playit-windows-x86.exe",
            "hash": "8eda23bdd7d55b30c37d50344f7010a4f3e8fc032554094890328123312b347b"
        },
        "64bit": {
            "url": "https://github.com/playit-cloud/playit-agent/releases/download/v1.0.10/playit-windows-x86_64.exe",
            "hash": "97ad38fcbd1c4fafcb84a99c0b1b1ba216f76ef5372ae2f6ef142652a1239ad4"
        }
    },
    "pre_install": "Rename-Item -Path $dir/$fname -NewName $dir/playit.exe",
    "bin": "playit.exe",
    "shortcuts": [
        [
            "playit.exe",
            "Playit.gg"
        ]
    ],
    "checkver": {
        "github": "https://github.com/playit-cloud/playit-agent"
    },
    "autoupdate": {
        "architecture": {
            "32bit": {
                "url": "https://github.com/playit-cloud/playit-agent/releases/download/v$version/playit-windows-x86.exe"
            },
            "64bit": {
                "url": "https://github.com/playit-cloud/playit-agent/releases/download/v$version/playit-windows-x86_64.exe"
            }
        }
    }
}
