{
    "version": "2022.12.0+330-preview",
    "homepage": "https://www.rstudio.com/",
    "description": "An IDE for R, which includes a console, syntax-highlighting editor that supports direct code execution, as well as tools for plotting, history, debugging and workspace management.",
    "license": "AGPL-3.0-only",
    "architecture": {
        "64bit": {
            "url": "https://s3.amazonaws.com/rstudio-ide-build/electron/windows/RStudio-2022.12.0-preview-330.zip",
            "hash": "411cee42595357718f8de957e18431ac147ed74fd7980f1de6717c04a4f6de6a"
        }
    },
    "bin": [
        [
            "rstudio.exe",
            "rstudio-daily-electron"
        ]
    ],
    "shortcuts": [
        [
            "rstudio.exe",
            "RStudio Daily Electron"
        ]
    ],
    "checkver": {
        "url": "https://dailies.rstudio.com/rstudio/latest/index.json",
        "jsonpath": ".products.electron.platforms['windows-xcopy'].version",
        "regex": "(?<date>[\\d.]+)(?<type>-(daily|preview))?\\+(?<build>\\d+)",
        "replace": "${date}+${build}${type}"
    },
    "autoupdate": {
        "architecture": {
            "64bit": {
                "url": "https://s3.amazonaws.com/rstudio-ide-build/electron/windows/RStudio-$matchDate$matchType-$matchBuild.zip",
                "hash": {
                    "mode": "json",
                    "jsonpath": ".products.electron.platforms['windows-xcopy'].sha256",
                    "url": "https://dailies.rstudio.com/rstudio/latest/index.json"
                }
            }
        }
    }
}
