{
    "version": "1.3.2",
    "description": "LoRA Manager for Civit Models",
    "homepage": "https://github.com/hanbinhsh/SD-LoRA-Manager",
    "license": "Unknown",
    "architecture": {
        "64bit": {
            "url": "https://github.com/hanbinhsh/SD-LoRA-Manager/releases/download/1.3.2/SD_LoRA_Manager.exe",
            "hash": "1b42f27e14113de004e5f78de28dcf642a7a06f6cd86df6495ffdd3051bf6eb0"
        }
    },
    "shortcuts": [
        [
            "SD_LoRA_Manager.exe",
            "SD-LoRA-Manager"
        ]
    ],
    "persist": "config",
    "checkver": {
        "github": "https://github.com/hanbinhsh/SD-LoRA-Manager"
    },
    "autoupdate": {
        "url": "https://github.com/hanbinhsh/SD-LoRA-Manager/releases/download/$version/SD_LoRA_Manager.exe",
        "hash": {
            "mode": "extract",
            "url": "https://github.com/hanbinhsh/SD-LoRA-Manager/releases/expanded_assets/$version",
            "regex": "SD_LoRA_Manager.*\\.exe.*?sha256:$sha256"
        }
    }
}
