{
    "version": "0",
    "description": "Sordum's Defender Exclusion Tool. Add/Remove exclusions to Windows Defender.",
    "homepage": "https://www.sordum.org/defender-exclusion-tool",
    "license": {
        "identifier": "Freeware",
        "url": "https://www.sordum.org/eula/"
    },
    "url": "https://www.sordum.org/files/download/defender-exclusion-tool/ExcTool.zip",
    "hash": "4ce0fda5acb2d838dfad4484c07602c1f418f560484fed78496a77ae3b74ddb8",
    "extract_dir": "ExcTool_v0",
    "bin": "ExcTool.exe",
    "shortcuts": [
        [
            "ExcTool.exe",
            "Sordum\\Defender Exclusion Tool"
        ]
    ],
    "checkver": "v([\\d.]+)",
    "autoupdate": {
        "url": "https://www.sordum.org/files/download/defender-exclusion-tool/ExcTool.zip",
        "extract_dir": "ExcTool_v$version"
    }
}
