{
    "version": "2.7.1",
    "description": "Subfinder is a subdomain discovery tool that discovers valid subdomains for websites. Designed as a passive framework to be useful for bug bounties and safe for penetration testing.(Scoop bucket for Cybersecurity by whoopscs)",
    "homepage": "https://projectdiscovery.io",
    "license": "MIT",
    "notes": "Scoop bucket for Cybersecurity by whoopscs(https://github.com/whoopscs/scoop-security).",
    "architecture": {
        "32bit": {
            "url": "https://github.com/projectdiscovery/subfinder/releases/download/v2.7.1/subfinder_2.7.1_windows_386.zip",
            "hash": "4391f148b7f9d8187d15b42506b1dabbf820eba30250134318a464fa644f8497"
        },
        "64bit": {
            "url": "https://github.com/projectdiscovery/subfinder/releases/download/v2.7.1/subfinder_2.7.1_windows_amd64.zip",
            "hash": "bc3b1b58054e2d182556dff59348cdb49ad1c9dab02fc693dba192d743101e37"
        }
    },
    "bin": "subfinder.exe",
    "checkver": {
        "github": "https://github.com/projectdiscovery/subfinder"
    },
    "autoupdate": {
        "architecture": {
            "32bit": {
                "url": "https://github.com/projectdiscovery/subfinder/releases/download/v$version/subfinder_$version_windows_386.zip"
            },
            "64bit": {
                "url": "https://github.com/projectdiscovery/subfinder/releases/download/v$version/subfinder_$version_windows_amd64.zip"
            }
        }
    }
}
