{
    "homepage": "https://github.com/belowaverage-org/SuperGrate",
    "version": "1.3.5.0",
    "description": "A GUI that assists Microsoft's User State Migration Utility in performing remote migrations over a network connection.",
    "license": "GPL-3.0-only",
    "architecture": {
        "64bit": {
            "url": "https://github.com/belowaverage-org/SuperGrate/releases/download/1.3.5.0/Release.zip",
            "hash": "5dea740c96332bc33880e4a90b1da64557193e3d40e60881f3b0905c1e8303dd",
            "extract_dir": "Release",
            "pre_install": [
                "Move-Item \"$dir\\Release_64\\SuperGrate.exe\" \"$dir\"",
                "Remove-Item \"$dir\\Release*\" -Force -Recurse"
            ]
        },
        "32bit": {
            "url": "https://github.com/belowaverage-org/SuperGrate/releases/download/1.3.5.0/Release.zip",
            "hash": "5dea740c96332bc33880e4a90b1da64557193e3d40e60881f3b0905c1e8303dd",
            "extract_dir": "Release",
            "pre_install": [
                "Move-Item \"$dir\\Release\\SuperGrate.exe\" \"$dir\"",
                "Remove-Item \"$dir\\Release*\" -Force -Recurse"
            ]
        }
    },
    "shortcuts": [
        [
            "SuperGrate.exe",
            "SuperGrate"
        ]
    ],
    "checkver": "github",
    "autoupdate": {
        "architecture": {
            "64bit": {
                "url": "https://github.com/belowaverage-org/SuperGrate/releases/download/$version/Release.zip"
            },
            "32bit": {
                "url": "https://github.com/belowaverage-org/SuperGrate/releases/download/$version/Release.zip"
            }
        }
    }
}
