{
 "architecture": {
  "32bit": {
   "hash": "620518a46ae018fc5eee00b4e48ec66310422674f9a11b4261792ed3a48417fc",
   "url": "https://www.nirsoft.net/utils/taskschedulerview.zip"
  },
  "64bit": {
   "hash": "75f0c0256af499b50b77bca40e1aa75d52b6606b06a2d497da18cdd2f541181e",
   "url": "https://www.nirsoft.net/utils/taskschedulerview-x64.zip"
  }
 },
 "autoupdate": {
  "architecture": {
   "32bit": {
    "url": "https://www.nirsoft.net/utils/taskschedulerview.zip"
   },
   "64bit": {
    "url": "https://www.nirsoft.net/utils/taskschedulerview-x64.zip"
   }
  }
 },
 "bin": "TaskSchedulerView.exe",
 "checkver": "TaskSchedulerView v(\\d+\\.\\d\\d)",
 "description": "TaskSchedulerView is a simple tool for Windows Vista/7/8/10 that displays in a single table the list of all tasks from the Task Scheduler of Windows. It also allows you to easily disable/enable mutiple tasks at once. For every task, the following information is displayed: Task Name, Description, Status, Hidden (Yes/No), Last Run/Next Run Times, Task Folder, EXE filename or COM handler of the task, number of missed runs, and more...",
 "homepage": "https://www.nirsoft.net/utils/task_scheduler_view.html",
 "license": "freeware",
 "shortcuts": [
  [
   "TaskSchedulerView.exe",
   "NirSoft\\TaskSchedulerView - View Task Scheduler of Windows"
  ]
 ],
 "version": "1.71"
}