{
 "autoupdate": {
  "hash": {
   "regex": "MD5 Hash: +[\\w]{32}",
   "url": "https://portableapps.com/apps/games/usb-sudoku-portable"
  },
  "url": "https://downloads.sourceforge.net/portableapps/USBSudokuPortable_$version_English.paf.exe"
 },
 "bin": "USBSudokuPortable.exe",
 "checkver": {
  "re": "Version \\s+([\\w\\.]* for Win",
  "url": "https://portableapps.com/apps/games/usb-sudoku-portable"
 },
 "description": "Number placement puzzle game",
 "hash": "md5:e29a3115dedf925c27c9aea60e51601d",
 "homepage": "https://portableapps.com/apps/games/usb-sudoku-portable",
 "license": "",
 "persist": "Data",
 "post_install": "Remove-Item -LiteralPath \"$dir\\`$PLUGINSDIR\" -Force -Recurse",
 "shortcuts": [
  [
   "USBSudokuPortable.exe",
   "USBSudokuPortable"
  ]
 ],
 "url": "https://downloads.sourceforge.net/portableapps/USBSudokuPortable_2.0_English.paf.exe#/dl.7z",
 "version": "2.0"
}