{
    "version": "2023.02.08.19419",
    "description": "Unofficial daily builds for yt-dlp - a youtube-dl fork with additional features and fixes.",
    "homepage": "https://github.com/ytdl-patched/yt-dlp",
    "license": "Unlicense",
    "suggest": {
        "ffmpeg": "ffmpeg-nightly"
    },
    "architecture": {
        "64bit": {
            "url": "https://github.com/ytdl-patched/yt-dlp/releases/download/2023.02.08.19419/yt-dlp.exe",
            "hash": "sha512:fb17849eafd9667cfba29f02766627e74458c48f350b5990d1d3c6c35160f4d24a341f8f037642c4c3f45f7a008d83f5edca13d63cf2939ef415726b0acf32f8"
        },
        "32bit": {
            "url": "https://github.com/ytdl-patched/yt-dlp/releases/download/2023.02.08.19419/yt-dlp_x86.exe#/yt-dlp.exe",
            "hash": "sha512:d9ff44c0170f05c14aa22ea14f51edb859c3455680a854bb59533b73551beb5430a2d2b7c0e3f3478eb91fb95443da275440f29710156ada0c83d181449484c9"
        }
    },
    "bin": "yt-dlp.exe",
    "pre_install": "if (-not (Test-Path \"$persist_dir\\yt-dlp.conf\")) { New-Item \"$dir\\yt-dlp.conf\" -ItemType file | Out-Null }",
    "persist": [
        "yt-dlp.conf",
        "ytdlp_plugins"
    ],
    "checkver": "github",
    "autoupdate": {
        "architecture": {
            "64bit": {
                "url": "https://github.com/ytdl-patched/yt-dlp/releases/download/$version/yt-dlp.exe"
            },
            "32bit": {
                "url": "https://github.com/ytdl-patched/yt-dlp/releases/download/$version/yt-dlp_x86.exe#/yt-dlp.exe"
            }
        },
        "hash": {
            "url": "$baseurl/SHA2-512SUMS"
        }
    }
}
