{
    "homepage": "https://yuzu-emu.org/",
    "description": "Experimental emulator for the Nintendo Switch",
    "version": "0-701",
    "license": "GPL-2.0-only",
    "architecture": {
        "64bit": {
            "url": "https://github.com/yuzu-emu/yuzu-mainline/releases/download/mainline-0-701/yuzu-windows-msvc-20210726-fb9b5898b.7z",
            "hash": "1ed3ac7c53c3ba7072fe56d0d2a82772b5fcc3971df07b67cc3958da9ec11f8d"
        }
    },
    "extract_dir": "yuzu-windows-msvc",
    "shortcuts": [
        [
            "yuzu.exe",
            "Yuzu"
        ]
    ],
    "checkver": {
        "github": "https://github.com/yuzu-emu/yuzu-mainline",
        "regex": "download/mainline-([\\d.-]+)/yuzu-windows-msvc-(?<date>[\\d]{8})-(?<commit>[\\da-f]+).7z"
    },
    "autoupdate": {
        "architecture": {
            "64bit": {
                "url": "https://github.com/yuzu-emu/yuzu-mainline/releases/download/mainline-$version/yuzu-windows-msvc-$matchDate-$matchCommit.7z"
            }
        }
    }
}
